{
  "filename": "000.through-a-song-darkly.2025-8-28.txt",
  "contentHash": "28f6bbbad24c8586b0bfd3ef8e2e87e2fbf3fd5037e2448ce4fc5fcfbeccf18d",
  "totalLines": 3981,
  "windowCount": 11,
  "segments": [
    {
      "startLine": 1,
      "endLine": 151,
      "label": "ooc",
      "confidence": "high",
      "oneLineSummary": "Players discuss Windows update issues, Discord problems, and technical troubleshooting"
    },
    {
      "startLine": 152,
      "endLine": 206,
      "label": "ooc",
      "confidence": "high",
      "oneLineSummary": "Argyle recounts Denver Airport experiences: bus boarding inefficiency and passenger incompetence"
    },
    {
      "startLine": 207,
      "endLine": 237,
      "label": "ooc",
      "confidence": "high",
      "oneLineSummary": "Argyle tells story about Delta flight attendant confusion over water vs. iced coffee request"
    },
    {
      "startLine": 238,
      "endLine": 266,
      "label": "ooc",
      "confidence": "high",
      "oneLineSummary": "Argyle shares workplace joke about coffee: 'it's not my cup of tea'"
    },
    {
      "startLine": 267,
      "endLine": 380,
      "label": "ooc",
      "confidence": "high",
      "oneLineSummary": "Players discuss ISS decommissioning, reference frames, physics Reddit debates about pull-ups and treadmills"
    },
    {
      "startLine": 381,
      "endLine": 495,
      "label": "ooc",
      "confidence": "high",
      "oneLineSummary": "Players discuss physics, Reddit, third-party apps, NYT crossword paywall, and campaign background setup"
    },
    {
      "startLine": 496,
      "endLine": 546,
      "label": "ooc",
      "confidence": "high",
      "oneLineSummary": "Discussion of Notion campaign notes, previous campaign currencies, NPCs returning from campaign one"
    },
    {
      "startLine": 547,
      "endLine": 730,
      "label": "recap",
      "confidence": "high",
      "oneLineSummary": "Johnny recaps first mega session: fire, escape, breakfast, meeting Illmari and NPCs, investigating Flynn's death, sewers, augers, recovering body, satellite dish, Zorbon meeting"
    },
    {
      "startLine": 731,
      "endLine": 742,
      "label": "recap",
      "confidence": "high",
      "oneLineSummary": "Johnny recaps previous session: stole radar dish from roller rink, returned to Sin and Tonic, party leveled up"
    },
    {
      "startLine": 743,
      "endLine": 826,
      "label": "ooc",
      "confidence": "high",
      "oneLineSummary": "Players and GM discuss hero points, mythic points, and joke about Wheel of Fortune vowels; GM clarifies mattress history"
    },
    {
      "startLine": 827,
      "endLine": 895,
      "label": "ic",
      "confidence": "high",
      "oneLineSummary": "Argyle wakes and goes downstairs for breakfast; Anzu asks about Fanes and hearts, rolls Arcana 20 to learn about Belvedere's multiple hearts"
    },
    {
      "startLine": 896,
      "endLine": 970,
      "label": "ic",
      "confidence": "high",
      "oneLineSummary": "Party discusses fire repellent with Ginny the heart; orders breakfast; Johnny finds ornate fans; party plans next steps and shopping"
    },
    {
      "startLine": 971,
      "endLine": 1047,
      "label": "ic",
      "confidence": "high",
      "oneLineSummary": "Anzu wants to check on twins about radar dish investigation; discusses tuning it cautiously; twins mention Sentience Distributor and Embercall"
    },
    {
      "startLine": 1048,
      "endLine": 1080,
      "label": "ic",
      "confidence": "high",
      "oneLineSummary": "Party discusses acquiring equipment and weapons; characters negotiate with a merchant contact and track gold/silver inventory."
    },
    {
      "startLine": 1081,
      "endLine": 1183,
      "label": "rules",
      "confidence": "high",
      "oneLineSummary": "Players discuss equipment purchases, armor costs, discounts, and party finances; debate plate armor affordability"
    },
    {
      "startLine": 1184,
      "endLine": 1224,
      "label": "ic",
      "confidence": "high",
      "oneLineSummary": "Anouk offers scrapyard work; party decides to visit Johnny's contact for armor before taking jobs"
    },
    {
      "startLine": 1225,
      "endLine": 1340,
      "label": "ic",
      "confidence": "high",
      "oneLineSummary": "Party travels to seedier district via trolley; Anzu's raven Othello arrives; group heads to Undertable pawn shop"
    },
    {
      "startLine": 1341,
      "endLine": 1441,
      "label": "ic",
      "confidence": "high",
      "oneLineSummary": "Party enters Undertable pawn shop; Johnny reunites with Smiler the centaur fence; Smiler offers Benny a gun"
    },
    {
      "startLine": 1442,
      "endLine": 1600,
      "label": "ic",
      "confidence": "high",
      "oneLineSummary": "Party sells items to Smiler at pawn shop, negotiates radio price, Argyle gets new armor"
    },
    {
      "startLine": 1601,
      "endLine": 1667,
      "label": "ic",
      "confidence": "high",
      "oneLineSummary": "Party leaves pawn shop, heads toward scrapyard, Anzu examines Benny's permission slip"
    },
    {
      "startLine": 1668,
      "endLine": 1708,
      "label": "ic",
      "confidence": "high",
      "oneLineSummary": "Players ask questions about their characters' backgrounds in Belvedere; GM provides lore answers about education, children, and a vaguely familiar name."
    },
    {
      "startLine": 1709,
      "endLine": 1776,
      "label": "ic",
      "confidence": "high",
      "oneLineSummary": "Party discusses origins and backstories; Benny reveals Pulse spoke to him, gave glowing pick"
    },
    {
      "startLine": 1777,
      "endLine": 1820,
      "label": "ic",
      "confidence": "high",
      "oneLineSummary": "Party reacts to Benny's revelation; Argyle shows new business card, discusses parents with Scale"
    },
    {
      "startLine": 1821,
      "endLine": 1868,
      "label": "ic",
      "confidence": "high",
      "oneLineSummary": "Party discusses glowing items from dreams, Argyle's new business cards and licensing, and Argyle's parents' names (Aaron Cross and Joran Davinrock)"
    },
    {
      "startLine": 1869,
      "endLine": 1883,
      "label": "ic",
      "confidence": "high",
      "oneLineSummary": "GM narrates the party's arrival at Sableclutch Scrap, describing the neighborhood and its religious character."
    },
    {
      "startLine": 1884,
      "endLine": 1909,
      "label": "rules",
      "confidence": "high",
      "oneLineSummary": "GM calls for will saves; players roll, reroll using mythic points, and discuss results with mechanical focus."
    },
    {
      "startLine": 1910,
      "endLine": 1968,
      "label": "ic",
      "confidence": "high",
      "oneLineSummary": "Party arrives at Sableclutch Scrap, Johnny casts musical accompaniment, party discusses their recent gifts"
    },
    {
      "startLine": 1969,
      "endLine": 2030,
      "label": "ic",
      "confidence": "high",
      "oneLineSummary": "Party meets Copperjaw, dwarven scrapyard owner; Benny shakes his hand and receives handcuffed suitcase job for 100 gold"
    },
    {
      "startLine": 2031,
      "endLine": 2089,
      "label": "ic",
      "confidence": "high",
      "oneLineSummary": "NPC Copperjaw assigns delivery job with heavy magical suitcase; warns of potential ambush by interested parties."
    },
    {
      "startLine": 2090,
      "endLine": 2100,
      "label": "ooc",
      "confidence": "high",
      "oneLineSummary": "Players and GM banter about tire companies and world-building details; off-topic tangent about Michelin and Chorath."
    },
    {
      "startLine": 2101,
      "endLine": 2124,
      "label": "ooc",
      "confidence": "high",
      "oneLineSummary": "Players and GM discuss tire companies, restaurant guides, and real-world examples like Denver and Michelin stars—entirely out-of-character banter."
    },
    {
      "startLine": 2125,
      "endLine": 2180,
      "label": "ic",
      "confidence": "high",
      "oneLineSummary": "Copperjaw gives Diamond District address, Johnny prestidigitates party clean, confirms doorman details and payment"
    },
    {
      "startLine": 2181,
      "endLine": 2240,
      "label": "ic",
      "confidence": "high",
      "oneLineSummary": "Party negotiates payment details with Copperjaw, discusses the briefcase delivery job, and prepares to leave the junkyard"
    },
    {
      "startLine": 2241,
      "endLine": 2283,
      "label": "rules",
      "confidence": "high",
      "oneLineSummary": "Discussion of Anzu's animal companion's perception modifier and mechanics of an ability allowing one-minute eye-contact viewing once per ten minutes."
    },
    {
      "startLine": 2284,
      "endLine": 2290,
      "label": "ic",
      "confidence": "high",
      "oneLineSummary": "Players announce they're stepping away to use the restroom during the campaign session."
    },
    {
      "startLine": 2291,
      "endLine": 2333,
      "label": "ooc",
      "confidence": "high",
      "oneLineSummary": "Players discuss character identities and backstories out of character, joking about Benny's character being a pug"
    },
    {
      "startLine": 2334,
      "endLine": 2372,
      "label": "ic",
      "confidence": "high",
      "oneLineSummary": "Party walks through town while Johnny questions Benny about entertainment; GM describes perception checks and suspicious figure following them."
    },
    {
      "startLine": 2373,
      "endLine": 2403,
      "label": "ic",
      "confidence": "high",
      "oneLineSummary": "GM narrates party's journey, describes attention drawn by Benny's suitcase, and players establish marching order for continued travel."
    },
    {
      "startLine": 2404,
      "endLine": 2427,
      "label": "ooc",
      "confidence": "high",
      "oneLineSummary": "Players and GM discuss character appearance and race in a lighthearted meta conversation about a character's elven features."
    },
    {
      "startLine": 2428,
      "endLine": 2540,
      "label": "combat",
      "confidence": "high",
      "oneLineSummary": "Goblin pickpocket attempts to steal from Johnny, party pursues, then Black Line cops approach after commotion"
    },
    {
      "startLine": 2541,
      "endLine": 2559,
      "label": "ic",
      "confidence": "high",
      "oneLineSummary": "Anzu's bird Othello spots two Blackline cops approaching; they're not Threshold Authority."
    },
    {
      "startLine": 2560,
      "endLine": 2597,
      "label": "ic",
      "confidence": "high",
      "oneLineSummary": "Johnny persuades cops to pursue pickpocket; gives contact info via Copperjaw at Sableclutch scrap."
    },
    {
      "startLine": 2598,
      "endLine": 2626,
      "label": "ic",
      "confidence": "high",
      "oneLineSummary": "Argyle and Anzu scout for threats; cops position themselves to box in the party."
    },
    {
      "startLine": 2627,
      "endLine": 2678,
      "label": "ic",
      "confidence": "high",
      "oneLineSummary": "Argyle questions cops' ID; they mention delivery job and leave after exchanging names."
    },
    {
      "startLine": 2679,
      "endLine": 2738,
      "label": "ic",
      "confidence": "high",
      "oneLineSummary": "Party debates attacking cops; Othello follows cops who vanish; group heads to trolley station."
    },
    {
      "startLine": 2739,
      "endLine": 2768,
      "label": "ic",
      "confidence": "high",
      "oneLineSummary": "Othello scouts the area and loses sight of the cops; party makes it back to the trolley station without incident."
    },
    {
      "startLine": 2769,
      "endLine": 2773,
      "label": "ic",
      "confidence": "high",
      "oneLineSummary": "Party arrives at trolley station and waits for train; GM calls for perception check."
    },
    {
      "startLine": 2774,
      "endLine": 2797,
      "label": "rules",
      "confidence": "high",
      "oneLineSummary": "Rules discussion about vehicle costs, transport between city areas, and slide device mechanics."
    },
    {
      "startLine": 2798,
      "endLine": 2824,
      "label": "ic",
      "confidence": "high",
      "oneLineSummary": "Party arrives at trolley station; perceives waiting passengers; tram arrives and doors open."
    },
    {
      "startLine": 2825,
      "endLine": 2851,
      "label": "ic",
      "confidence": "high",
      "oneLineSummary": "Party boards tram; Benny sits by window; Argyle attempts to talk to other passengers."
    },
    {
      "startLine": 2852,
      "endLine": 2889,
      "label": "ic",
      "confidence": "high",
      "oneLineSummary": "Argyle makes society check on passengers; learns they're factory workers and lost tourists."
    },
    {
      "startLine": 2890,
      "endLine": 2900,
      "label": "ic",
      "confidence": "high",
      "oneLineSummary": "Tram moves to Void 2; more passengers board; Johnny spots goblin factory worker eyeing briefcase."
    },
    {
      "startLine": 2901,
      "endLine": 2902,
      "label": "ic",
      "confidence": "high",
      "oneLineSummary": "Party boards tram, GM describes passengers; Argyle guards child; more passengers board at next stops"
    },
    {
      "startLine": 2903,
      "endLine": 2920,
      "label": "ic",
      "confidence": "high",
      "oneLineSummary": "Tram moves to Void 2; more passengers board; Johnny spots goblin factory worker eyeing briefcase."
    },
    {
      "startLine": 2921,
      "endLine": 2924,
      "label": "ic",
      "confidence": "high",
      "oneLineSummary": "Johnny gives orders to spread a message and keep watch on Anaïs; Benny comments on private trams."
    },
    {
      "startLine": 2925,
      "endLine": 2960,
      "label": "ic",
      "confidence": "high",
      "oneLineSummary": "Tram reaches destination; party disembarks; GM offers taxi or walking; party decides to walk"
    },
    {
      "startLine": 2961,
      "endLine": 3027,
      "label": "ic",
      "confidence": "high",
      "oneLineSummary": "Party checks for followers, finds none; routes through alleys toward destination; GM describes path options"
    },
    {
      "startLine": 3028,
      "endLine": 3083,
      "label": "ic",
      "confidence": "high",
      "oneLineSummary": "Party walks through alley; two office workers transform into fleshy creatures; combat imminent"
    },
    {
      "startLine": 3084,
      "endLine": 3260,
      "label": "combat",
      "confidence": "high",
      "oneLineSummary": "Initiative rolled; rules discussion on rune progression and weapon bonuses; Argyle and Benny attack creatures; combat begins"
    },
    {
      "startLine": 3261,
      "endLine": 3349,
      "label": "combat",
      "confidence": "high",
      "oneLineSummary": "Benny intimidates Ugathal I, Ugathal II attacks Argyle and grabs him, Benny interrupts with opportunity attack"
    },
    {
      "startLine": 3350,
      "endLine": 3411,
      "label": "combat",
      "confidence": "high",
      "oneLineSummary": "Johnny casts Courageous Anthem and Soothe, demoralizes Ugathal II, recites melancholy library poem"
    },
    {
      "startLine": 3412,
      "endLine": 3478,
      "label": "combat",
      "confidence": "high",
      "oneLineSummary": "Anzu recalls knowledge on creatures, casts Telekinetic Rend on both Ugathals, shields herself"
    },
    {
      "startLine": 3479,
      "endLine": 3551,
      "label": "combat",
      "confidence": "high",
      "oneLineSummary": "Argyle strikes Ugathal I twice, treats wounds with critical success, gains mythic point back"
    },
    {
      "startLine": 3552,
      "endLine": 3615,
      "label": "combat",
      "confidence": "high",
      "oneLineSummary": "Benny kills Ugathal I with intimidating strike, Ugathal II attempts blood nourishment but gets interrupted by Johnny"
    },
    {
      "startLine": 3616,
      "endLine": 3799,
      "label": "combat",
      "confidence": "high",
      "oneLineSummary": "Combat continues: Johnny uses distracting performance, Anzu attacks with telekinetic projectile, Argyle finishes off the Ugathal with a great axe strike."
    },
    {
      "startLine": 3800,
      "endLine": 3819,
      "label": "ic",
      "confidence": "high",
      "oneLineSummary": "Party searches the Ugathal corpses, finds two black line badges inside the flesh."
    },
    {
      "startLine": 3820,
      "endLine": 3830,
      "label": "ooc",
      "confidence": "high",
      "oneLineSummary": "Players and GM banter about adding 'Agent of' to business cards and joking about fraud."
    },
    {
      "startLine": 3831,
      "endLine": 3876,
      "label": "ooc",
      "confidence": "high",
      "oneLineSummary": "Post-combat discussion: players and GM discuss enemy stats, crit rolls, weapon builds, and reactive strike mechanics in a casual, joking tone."
    },
    {
      "startLine": 3877,
      "endLine": 3900,
      "label": "rules",
      "confidence": "high",
      "oneLineSummary": "Rules discussion: weapon potency benefits for spellcasters, armor potency from explorer's clothing, hand wraps for unarmed strikes."
    },
    {
      "startLine": 3901,
      "endLine": 3981,
      "label": "ooc",
      "confidence": "high",
      "oneLineSummary": "Players discuss scheduling (Johnny to Japan, Anzu to Italy, Argyle's wedding), Johnny's book manuscript, and say goodbyes."
    }
  ]
}
